easyargs/__init__.py
easyargs/decorators.py
easyargs/main.py
easyargs/parsers.py
easyargs-0.9.4.dist-info/DESCRIPTION.rst
easyargs-0.9.4.dist-info/METADATA
easyargs-0.9.4.dist-info/RECORD
easyargs-0.9.4.dist-info/WHEEL
easyargs-0.9.4.dist-info/metadata.json
easyargs-0.9.4.dist-info/top_level.txt
